phovea_processing_queue/__init__.py
phovea_processing_queue/config.json
phovea_processing_queue/processing.py
phovea_processing_queue/security.py
phovea_processing_queue/server.py
phovea_processing_queue/task_definition.py
phovea_processing_queue/tasks.py
phovea_processing_queue-6.0.0.dist-info/LICENSE
phovea_processing_queue-6.0.0.dist-info/METADATA
phovea_processing_queue-6.0.0.dist-info/WHEEL
phovea_processing_queue-6.0.0.dist-info/entry_points.txt
phovea_processing_queue-6.0.0.dist-info/top_level.txt
phovea_processing_queue-6.0.0.dist-info/RECORD
