Metadata-Version: 2.1
Name: phovea-processing-queue
Version: 6.0.0
Summary: Process long-running tasks in the background using Celery.
Home-page: https://phovea.caleydo.org
Author: The Caleydo Team
Author-email: contact@caleydo.org
License: BSD-3-Clause
Platform: UNKNOWN
Classifier: Intended Audience :: Developers
Classifier: Operating System :: OS Independent
Classifier: License :: OSI Approved :: BSD License
Classifier: Programming Language :: Python
Classifier: Programming Language :: Python :: 3.7
Requires-Dist: celery[auth,msgpack,redis] (==4.2.2)
Requires-Dist: phovea-data-redis (<8.0.0,>=7.0.0)
Requires-Dist: phovea-server (<8.0.0,>=7.0.0)
